edgeimpulse_api/__init__.py
edgeimpulse_api/api/__init__.py
edgeimpulse_api/api/classify_api.py
edgeimpulse_api/api/deployment_api.py
edgeimpulse_api/api/devices_api.py
edgeimpulse_api/api/dsp_api.py
edgeimpulse_api/api/email_verification_api.py
edgeimpulse_api/api/export_api.py
edgeimpulse_api/api/impulse_api.py
edgeimpulse_api/api/integrations_api.py
edgeimpulse_api/api/jobs_api.py
edgeimpulse_api/api/learn_api.py
edgeimpulse_api/api/login_api.py
edgeimpulse_api/api/optimization_api.py
edgeimpulse_api/api/organization_blocks_api.py
edgeimpulse_api/api/organization_create_project_api.py
edgeimpulse_api/api/organization_data_api.py
edgeimpulse_api/api/organization_data_campaigns_api.py
edgeimpulse_api/api/organization_jobs_api.py
edgeimpulse_api/api/organization_pipelines_api.py
edgeimpulse_api/api/organization_portals_api.py
edgeimpulse_api/api/organizations_api.py
edgeimpulse_api/api/performance_calibration_api.py
edgeimpulse_api/api/post_processing_api.py
edgeimpulse_api/api/projects_api.py
edgeimpulse_api/api/raw_data_api.py
edgeimpulse_api/api/upload_portal_api.py
edgeimpulse_api/api/user_api.py
edgeimpulse_api/api/whitelabels_api.py
edgeimpulse_api/api_client.py
edgeimpulse_api/configuration.py
edgeimpulse_api/exceptions.py
edgeimpulse_api/models/__init__.py
edgeimpulse_api/models/accept_eula_request.py
edgeimpulse_api/models/activate_user_by_third_party_activation_code_request.py
edgeimpulse_api/models/activate_user_or_verify_email_request.py
edgeimpulse_api/models/add_api_key_request.py
edgeimpulse_api/models/add_api_key_response.py
edgeimpulse_api/models/add_api_key_response_all_of.py
edgeimpulse_api/models/add_collaborator_request.py
edgeimpulse_api/models/add_hmac_key_request.py
edgeimpulse_api/models/add_keras_files_request.py
edgeimpulse_api/models/add_member_request.py
edgeimpulse_api/models/add_organization_api_key_request.py
edgeimpulse_api/models/add_organization_api_key_request_all_of.py
edgeimpulse_api/models/add_organization_bucket_request.py
edgeimpulse_api-1.83.4.dist-info/LICENSE
edgeimpulse_api-1.83.4.dist-info/METADATA
edgeimpulse_api-1.83.4.dist-info/WHEEL
edgeimpulse_api-1.83.4.dist-info/RECORD
